{"Name": "['Nicolas']", "Lastname": "['Ramos']", "Lastname2": "['Parra']", "Birthday": "['13/02/1998']"}
{"Name": "['Hugo']", "Lastname": "['Hernandez']", "Lastname2": "['Vicente']", "Birthday": "['28/06/2013']"}
{"Name": "['Rafael']", "Lastname": "['Torres']", "Lastname2": "['Bravo']", "Birthday": "['11/01/1986']"}
{"Name": "['Benjamin']", "Lastname": "['Ramos']", "Lastname2": "['Soto']", "Birthday": "['28/08/1986']"}
{"Name": "['Ada']", "Lastname": "['Ramos']", "Lastname2": "['Pastor']", "Birthday": "['29/04/1988']"}
{"Name": "['Andrea']", "Lastname": "['Cabrera']", "Lastname2": "['Ibanhez']", "Birthday": "['20/03/1997']"}
{"Name": "['Dulce']", "Lastname": "['Medina']", "Lastname2": "['Navarro']", "Birthday": "['12/08/1994']"}
{"Name": "['Regina']", "Lastname": "['Duran']", "Lastname2": "['Serrano']", "Birthday": "['30/11/1983']"}
{"Name": "['Perla']", "Lastname": "['Vicente']", "Lastname2": "['Cortes']", "Birthday": "['09/12/2017']"}
{"Name": "['Vivian']", "Lastname": "['Perez']", "Lastname2": "['Fuentes']", "Birthday": "['19/08/1982']"}
{"Name": "['Sofia']", "Lastname": "['Cano']", "Lastname2": "['Crespo']", "Birthday": "['19/07/2019']"}
{"Name": "['Angel']", "Lastname": "['Cruz']", "Lastname2": "['Delgado']", "Birthday": "['17/01/2012']"}
{"Name": "['Alana']", "Lastname": "['Medina']", "Lastname2": "['Castro']", "Birthday": "['27/02/2019']"}
{"Name": "['Rodrigo']", "Lastname": "['Iglesias']", "Lastname2": "['Ortega']", "Birthday": "['14/04/2009']"}
{"Name": "['Rosa']", "Lastname": "['Moreno']", "Lastname2": "['Herrera']", "Birthday": "['28/05/1988']"}
{"Name": "['Ana']", "Lastname": "['Hidalgo']", "Lastname2": "['Roman']", "Birthday": "['30/08/2009']"}
{"Name": "['Josue']", "Lastname": "['Munhoz']", "Lastname2": "['Pastor']", "Birthday": "['25/09/2006']"}
{"Name": "['Gabriel']", "Lastname": "['Iglesias']", "Lastname2": "['Herrero']", "Birthday": "['11/06/1987']"}
{"Name": "['Isabel']", "Lastname": "['Lozano']", "Lastname2": "['Diaz']", "Birthday": "['01/02/2011']"}
{"Name": "['Ernesto']", "Lastname": "['Sanchez']", "Lastname2": "['Gallego']", "Birthday": "['05/02/2008']"}
{"Name": "['Fernanda']", "Lastname": "['Gonzalez']", "Lastname2": "['Ferrer']", "Birthday": "['13/06/2006']"}
{"Name": "['Alana']", "Lastname": "['Soto']", "Lastname2": "['Benitez']", "Birthday": "['14/01/2021']"}
{"Name": "['Sara']", "Lastname": "['Sanchez']", "Lastname2": "['Cruz']", "Birthday": "['15/10/2005']"}
{"Name": "['Serena']", "Lastname": "['Serrano']", "Lastname2": "['Crespo']", "Birthday": "['19/02/1991']"}
{"Name": "['Lucas']", "Lastname": "['Roman']", "Lastname2": "['Ferrer']", "Birthday": "['30/01/2007']"}
{"Name": "['Guadalupe']", "Lastname": "['Nunhez']", "Lastname2": "['Sanz']", "Birthday": "['19/02/2006']"}
{"Name": "['Gloria']", "Lastname": "['Castillo']", "Lastname2": "['Gutierrez']", "Birthday": "['22/02/2019']"}
{"Name": "['Oscar']", "Lastname": "['Santiago']", "Lastname2": "['Herrera']", "Birthday": "['27/06/1982']"}
{"Name": "['Angela']", "Lastname": "['Caballero']", "Lastname2": "['Dominguez']", "Birthday": "['05/01/2012']"}
{"Name": "['Carlos']", "Lastname": "['Soler']", "Lastname2": "['Rojas']", "Birthday": "['19/03/1995']"}
{"Name": "['Arturo']", "Lastname": "['Blanco']", "Lastname2": "['Jimenez']", "Birthday": "['07/01/1997']"}
{"Name": "['America']", "Lastname": "['Flores']", "Lastname2": "['Cortes']", "Birthday": "['09/11/2003']"}
{"Name": "['Joel']", "Lastname": "['Vega']", "Lastname2": "['Perez']", "Birthday": "['28/07/1998']"}
{"Name": "['Santiago']", "Lastname": "['Diaz']", "Lastname2": "['Munhoz']", "Birthday": "['05/05/2016']"}
{"Name": "['Regina']", "Lastname": "['Arias']", "Lastname2": "['Calvo']", "Birthday": "['09/07/1985']"}
{"Name": "['Linda']", "Lastname": "['Santos']", "Lastname2": "['Nieto']", "Birthday": "['02/06/2005']"}
{"Name": "['Alexis']", "Lastname": "['Guerrero']", "Lastname2": "['Mora']", "Birthday": "['22/09/1990']"}
{"Name": "['Saul']", "Lastname": "['Lozano']", "Lastname2": "['Morales']", "Birthday": "['11/09/2008']"}
{"Name": "['Daniela']", "Lastname": "['Suarez']", "Lastname2": "['Lozano']", "Birthday": "['23/08/1994']"}
{"Name": "['Ximena']", "Lastname": "['Santiago']", "Lastname2": "['Delgado']", "Birthday": "['18/02/1990']"}
{"Name": "['Alexis']", "Lastname": "['Arias']", "Lastname2": "['Esteban']", "Birthday": "['18/12/2013']"}
{"Name": "['Elisa']", "Lastname": "['Parra']", "Lastname2": "['Leon']", "Birthday": "['05/02/1992']"}
{"Name": "['Abel']", "Lastname": "['Delgado']", "Lastname2": "['Fernandez']", "Birthday": "['21/03/2021']"}
{"Name": "['Elsa']", "Lastname": "['Parra']", "Lastname2": "['Gomez']", "Birthday": "['05/01/1991']"}
{"Name": "['Serena']", "Lastname": "['Hernandez']", "Lastname2": "['Herrera']", "Birthday": "['23/02/1982']"}
{"Name": "['Gloria']", "Lastname": "['Rojas']", "Lastname2": "['Gonzalez']", "Birthday": "['14/06/2004']"}
{"Name": "['Virginia']", "Lastname": "['Rojas']", "Lastname2": "['Ramirez']", "Birthday": "['24/07/1994']"}
{"Name": "['Julio']", "Lastname": "['Gutierrez']", "Lastname2": "['Morales']", "Birthday": "['28/06/1990']"}
{"Name": "['Angelina']", "Lastname": "['Romero']", "Lastname2": "['Vargas']", "Birthday": "['08/07/2021']"}
{"Name": "['Amaya']", "Lastname": "['Montero']", "Lastname2": "['Romero']", "Birthday": "['17/05/1994']"}
{"Name": "['Miriam']", "Lastname": "['Alonso']", "Lastname2": "['Lozano']", "Birthday": "['03/04/2013']"}
{"Name": "['Julia']", "Lastname": "['Iglesias']", "Lastname2": "['Romero']", "Birthday": "['18/12/2013']"}
{"Name": "['Francisco']", "Lastname": "['Ramos']", "Lastname2": "['Pascual']", "Birthday": "['10/03/1990']"}
{"Name": "['Perla']", "Lastname": "['Duran']", "Lastname2": "['Saez']", "Birthday": "['06/10/2013']"}
{"Name": "['Linda']", "Lastname": "['Torres']", "Lastname2": "['Parra']", "Birthday": "['19/03/1985']"}
{"Name": "['Mateo']", "Lastname": "['Duran']", "Lastname2": "['Guerrero']", "Birthday": "['15/07/2016']"}
{"Name": "['Claudia']", "Lastname": "['Gimenez']", "Lastname2": "['Alonso']", "Birthday": "['13/09/2004']"}
{"Name": "['Fernanda']", "Lastname": "['Duran']", "Lastname2": "['Munhoz']", "Birthday": "['02/06/2014']"}
{"Name": "['Alana']", "Lastname": "['Jimenez']", "Lastname2": "['Flores']", "Birthday": "['10/12/2019']"}
{"Name": "['Victoria']", "Lastname": "['Gimenez']", "Lastname2": "['Carmona']", "Birthday": "['04/07/2018']"}
{"Name": "['Marco']", "Lastname": "['Iglesias']", "Lastname2": "['Ortega']", "Birthday": "['03/01/2007']"}
{"Name": "['Alexis']", "Lastname": "['Vargas']", "Lastname2": "['Suarez']", "Birthday": "['17/10/2006']"}
{"Name": "['Adrian']", "Lastname": "['Campos']", "Lastname2": "['Vicente']", "Birthday": "['06/07/2001']"}
{"Name": "['Emilia']", "Lastname": "['Iglesias']", "Lastname2": "['Arias']", "Birthday": "['28/09/2007']"}
{"Name": "['Marina']", "Lastname": "['Diez']", "Lastname2": "['Cruz']", "Birthday": "['08/10/1987']"}
{"Name": "['Iris']", "Lastname": "['Guerrero']", "Lastname2": "['Jimenez']", "Birthday": "['03/05/2005']"}
{"Name": "['Tomas']", "Lastname": "['Gil']", "Lastname2": "['Delgado']", "Birthday": "['26/08/1985']"}
{"Name": "['Guadalupe']", "Lastname": "['Reyes']", "Lastname2": "['Serrano']", "Birthday": "['06/04/1991']"}
{"Name": "['Clara']", "Lastname": "['Gomez']", "Lastname2": "['Gutierrez']", "Birthday": "['31/03/2017']"}
{"Name": "['Abraham']", "Lastname": "['Delgado']", "Lastname2": "['Fernandez']", "Birthday": "['19/11/1987']"}
{"Name": "['Jairo']", "Lastname": "['Carmona']", "Lastname2": "['Soto']", "Birthday": "['23/01/2021']"}
{"Name": "['Joel']", "Lastname": "['Marin']", "Lastname2": "['Munhoz']", "Birthday": "['15/03/2001']"}
{"Name": "['Gustavo']", "Lastname": "['Diez']", "Lastname2": "['Cabrera']", "Birthday": "['03/01/2008']"}
{"Name": "['Pedro']", "Lastname": "['Ortega']", "Lastname2": "['Mora']", "Birthday": "['09/11/2018']"}
{"Name": "['Israel']", "Lastname": "['Ruiz']", "Lastname2": "['Vidal']", "Birthday": "['12/04/1986']"}
{"Name": "['Ernesto']", "Lastname": "['Gutierrez']", "Lastname2": "['Moya']", "Birthday": "['30/12/2013']"}
{"Name": "['Dulce']", "Lastname": "['Fuentes']", "Lastname2": "['Munhoz']", "Birthday": "['12/05/2007']"}
{"Name": "['Juliana']", "Lastname": "['Romero']", "Lastname2": "['Carrasco']", "Birthday": "['17/07/1982']"}
{"Name": "['Alejandra']", "Lastname": "['Castillo']", "Lastname2": "['Munhoz']", "Birthday": "['21/06/1983']"}
{"Name": "['Matias']", "Lastname": "['Aguilar']", "Lastname2": "['Reyes']", "Birthday": "['22/08/2015']"}
{"Name": "['Israel']", "Lastname": "['Sanchez']", "Lastname2": "['Santos']", "Birthday": "['22/10/2018']"}
{"Name": "['Carlos']", "Lastname": "['Alonso']", "Lastname2": "['Santos']", "Birthday": "['12/04/1983']"}
{"Name": "['Alonzo']", "Lastname": "['Castro']", "Lastname2": "['Navarro']", "Birthday": "['03/03/2010']"}
{"Name": "['America']", "Lastname": "['Ortega']", "Lastname2": "['Pascual']", "Birthday": "['02/10/2019']"}
{"Name": "['Melina']", "Lastname": "['Gutierrez']", "Lastname2": "['Delgado']", "Birthday": "['08/07/2016']"}
{"Name": "['Sandra']", "Lastname": "['Esteban']", "Lastname2": "['Nieto']", "Birthday": "['02/11/2010']"}
{"Name": "['Diana']", "Lastname": "['Serrano']", "Lastname2": "['Navarro']", "Birthday": "['07/02/1984']"}
{"Name": "['Natalia']", "Lastname": "['Cano']", "Lastname2": "['Prieto']", "Birthday": "['12/09/2001']"}
{"Name": "['Luis']", "Lastname": "['Vicente']", "Lastname2": "['Carmona']", "Birthday": "['29/05/1993']"}
{"Name": "['Sergio']", "Lastname": "['Vazquez']", "Lastname2": "['Perez']", "Birthday": "['28/02/2018']"}
{"Name": "['Daniela']", "Lastname": "['Prieto']", "Lastname2": "['Munhoz']", "Birthday": "['26/05/2020']"}
{"Name": "['Julian']", "Lastname": "['Iglesias']", "Lastname2": "['Vidal']", "Birthday": "['11/03/1993']"}
{"Name": "['Daniella']", "Lastname": "['Mendez']", "Lastname2": "['Caballero']", "Birthday": "['21/10/1993']"}
{"Name": "['Elisa']", "Lastname": "['Fuentes']", "Lastname2": "['Gutierrez']", "Birthday": "['27/04/2007']"}
{"Name": "['Juliana']", "Lastname": "['Nieto']", "Lastname2": "['Nunhez']", "Birthday": "['28/01/1986']"}
{"Name": "['Pedro']", "Lastname": "['Gallego']", "Lastname2": "['Calvo']", "Birthday": "['09/12/2017']"}
{"Name": "['Ezequiel']", "Lastname": "['Morales']", "Lastname2": "['Fernandez']", "Birthday": "['26/06/1996']"}
{"Name": "['Angelica']", "Lastname": "['Gomez']", "Lastname2": "['Vazquez']", "Birthday": "['14/01/1995']"}
{"Name": "['Ada']", "Lastname": "['Penha']", "Lastname2": "['Velasco']", "Birthday": "['20/11/2012']"}
{"Name": "['Jazmin']", "Lastname": "['Ruiz']", "Lastname2": "['Gallardo']", "Birthday": "['13/10/2008']"}
{"Name": "['Jimena']", "Lastname": "['Vargas']", "Lastname2": "['Cortes']", "Birthday": "['22/01/2012']"}
{"Name": "['Mateo']", "Lastname": "['Lopez']", "Lastname2": "['Rubio']", "Birthday": "['08/09/2009']"}
{"Name": "['Rosa']", "Lastname": "['Nunhez']", "Lastname2": "['Marin']", "Birthday": "['15/04/2001']"}
{"Name": "['Linda']", "Lastname": "['Torres']", "Lastname2": "['Santana']", "Birthday": "['21/09/2009']"}
{"Name": "['Rodrigo']", "Lastname": "['Mendez']", "Lastname2": "['Diez']", "Birthday": "['14/11/2008']"}
{"Name": "['Lia']", "Lastname": "['Herrero']", "Lastname2": "['Ramos']", "Birthday": "['16/10/1982']"}
{"Name": "['Alicia']", "Lastname": "['Hernandez']", "Lastname2": "['Garrido']", "Birthday": "['06/11/2012']"}
{"Name": "['Mariana']", "Lastname": "['Saez']", "Lastname2": "['Mora']", "Birthday": "['13/01/2016']"}
{"Name": "['Jairo']", "Lastname": "['Leon']", "Lastname2": "['Caballero']", "Birthday": "['18/02/2014']"}
{"Name": "['Mario']", "Lastname": "['Medina']", "Lastname2": "['Montero']", "Birthday": "['27/02/2008']"}
{"Name": "['Angel']", "Lastname": "['Diaz']", "Lastname2": "['Herrero']", "Birthday": "['16/02/2002']"}
{"Name": "['Fernanda']", "Lastname": "['Cabrera']", "Lastname2": "['Ramirez']", "Birthday": "['31/03/2002']"}
{"Name": "['Benjamin']", "Lastname": "['Ferrer']", "Lastname2": "['Medina']", "Birthday": "['16/07/1998']"}
{"Name": "['Jorge']", "Lastname": "['Ferrer']", "Lastname2": "['Rojas']", "Birthday": "['16/09/2021']"}
{"Name": "['Elsa']", "Lastname": "['Vidal']", "Lastname2": "['Guerrero']", "Birthday": "['22/03/2000']"}
{"Name": "['Fernando']", "Lastname": "['Gil']", "Lastname2": "['Velasco']", "Birthday": "['26/12/1997']"}
{"Name": "['Diana']", "Lastname": "['Nunhez']", "Lastname2": "['Hernandez']", "Birthday": "['08/01/1995']"}
{"Name": "['Emiliano']", "Lastname": "['Cabrera']", "Lastname2": "['Marin']", "Birthday": "['18/07/1993']"}
{"Name": "['Jesus']", "Lastname": "['Castro']", "Lastname2": "['Flores']", "Birthday": "['08/11/1997']"}
{"Name": "['Sergio']", "Lastname": "['Vargas']", "Lastname2": "['Carmona']", "Birthday": "['18/04/2005']"}
{"Name": "['Ada']", "Lastname": "['Benitez']", "Lastname2": "['Calvo']", "Birthday": "['19/10/2005']"}
{"Name": "['Maximiliano']", "Lastname": "['Gutierrez']", "Lastname2": "['Reyes']", "Birthday": "['06/07/1994']"}
{"Name": "['Simon']", "Lastname": "['Soto']", "Lastname2": "['Esteban']", "Birthday": "['15/06/2001']"}
{"Name": "['Lia']", "Lastname": "['Fuentes']", "Lastname2": "['Gimenez']", "Birthday": "['16/10/1999']"}
{"Name": "['Juan']", "Lastname": "['Prieto']", "Lastname2": "['Gomez']", "Birthday": "['30/03/1984']"}
{"Name": "['Roman']", "Lastname": "['Esteban']", "Lastname2": "['Ferrer']", "Birthday": "['19/10/1989']"}
{"Name": "['Fabian']", "Lastname": "['Marquez']", "Lastname2": "['Arias']", "Birthday": "['15/11/2001']"}
{"Name": "['Julian']", "Lastname": "['Garrido']", "Lastname2": "['Alvarez']", "Birthday": "['08/10/1983']"}
{"Name": "['Emanuel']", "Lastname": "['Diaz']", "Lastname2": "['Sanchez']", "Birthday": "['26/01/1992']"}
{"Name": "['Fernanda']", "Lastname": "['Parra']", "Lastname2": "['Carmona']", "Birthday": "['20/09/2020']"}
{"Name": "['Ada']", "Lastname": "['Caballero']", "Lastname2": "['Diaz']", "Birthday": "['01/05/2020']"}
{"Name": "['Emilio']", "Lastname": "['Soto']", "Lastname2": "['Pascual']", "Birthday": "['03/10/2015']"}
{"Name": "['Sandra']", "Lastname": "['Bravo']", "Lastname2": "['Castro']", "Birthday": "['17/09/1992']"}
{"Name": "['Perla']", "Lastname": "['Hidalgo']", "Lastname2": "['Moya']", "Birthday": "['22/05/2017']"}
{"Name": "['Lorenzo']", "Lastname": "['Esteban']", "Lastname2": "['Ramirez']", "Birthday": "['25/03/2021']"}
{"Name": "['Jesus']", "Lastname": "['Ortiz']", "Lastname2": "['Gomez']", "Birthday": "['13/09/1992']"}
{"Name": "['Julian']", "Lastname": "['Dominguez']", "Lastname2": "['Esteban']", "Birthday": "['12/12/2008']"}
{"Name": "['Jaime']", "Lastname": "['Gil']", "Lastname2": "['Flores']", "Birthday": "['26/09/2007']"}
{"Name": "['Omar']", "Lastname": "['Rojas']", "Lastname2": "['Moreno']", "Birthday": "['21/08/2014']"}
{"Name": "['Fernanda']", "Lastname": "['Hernandez']", "Lastname2": "['Gallego']", "Birthday": "['12/12/2005']"}
{"Name": "['Linda']", "Lastname": "['Suarez']", "Lastname2": "['Vazquez']", "Birthday": "['29/03/2000']"}
{"Name": "['Alina']", "Lastname": "['Lorenzo']", "Lastname2": "['Caballero']", "Birthday": "['17/09/1997']"}
{"Name": "['Marisol']", "Lastname": "['Morales']", "Lastname2": "['Delgado']", "Birthday": "['03/07/2011']"}
{"Name": "['Angelica']", "Lastname": "['Campos']", "Lastname2": "['Gonzalez']", "Birthday": "['08/01/2017']"}
{"Name": "['Fernanda']", "Lastname": "['Romero']", "Lastname2": "['Iglesias']", "Birthday": "['18/03/1983']"}
{"Name": "['Victoria']", "Lastname": "['Ramirez']", "Lastname2": "['Gimenez']", "Birthday": "['06/11/1995']"}
{"Name": "['Cesar']", "Lastname": "['Santana']", "Lastname2": "['Marin']", "Birthday": "['26/03/1993']"}
{"Name": "['Paul']", "Lastname": "['Santos']", "Lastname2": "['Penha']", "Birthday": "['26/01/2015']"}
{"Name": "['Sergio']", "Lastname": "['Pascual']", "Lastname2": "['Rodriguez']", "Birthday": "['25/03/1991']"}
{"Name": "['Angel']", "Lastname": "['Garrido']", "Lastname2": "['Soler']", "Birthday": "['03/04/1991']"}
{"Name": "['Pablo']", "Lastname": "['Suarez']", "Lastname2": "['Morales']", "Birthday": "['08/12/2010']"}
{"Name": "['Roman']", "Lastname": "['Velasco']", "Lastname2": "['Vega']", "Birthday": "['24/01/1990']"}
{"Name": "['Brenda']", "Lastname": "['Lopez']", "Lastname2": "['Diez']", "Birthday": "['01/06/2021']"}
{"Name": "['Claudia']", "Lastname": "['Castro']", "Lastname2": "['Navarro']", "Birthday": "['03/05/2004']"}
{"Name": "['Saul']", "Lastname": "['Diaz']", "Lastname2": "['Suarez']", "Birthday": "['08/01/2004']"}
{"Name": "['Marisol']", "Lastname": "['Blanco']", "Lastname2": "['Castro']", "Birthday": "['20/07/2000']"}
{"Name": "['Linda']", "Lastname": "['Flores']", "Lastname2": "['Saez']", "Birthday": "['07/11/1999']"}
{"Name": "['Laura']", "Lastname": "['Penha']", "Lastname2": "['Prieto']", "Birthday": "['29/04/1986']"}
{"Name": "['Nicolas']", "Lastname": "['Vicente']", "Lastname2": "['Martin']", "Birthday": "['15/04/1998']"}
{"Name": "['Javier']", "Lastname": "['Gil']", "Lastname2": "['Perez']", "Birthday": "['12/03/1995']"}
{"Name": "['Angela']", "Lastname": "['Vidal']", "Lastname2": "['Gallego']", "Birthday": "['06/07/2000']"}
{"Name": "['Benjamin']", "Lastname": "['Aguilar']", "Lastname2": "['Ortega']", "Birthday": "['27/10/2021']"}
{"Name": "['Oliver']", "Lastname": "['Fuentes']", "Lastname2": "['Alvarez']", "Birthday": "['14/04/2006']"}
{"Name": "['Guadalupe']", "Lastname": "['Rodriguez']", "Lastname2": "['Castillo']", "Birthday": "['17/08/2015']"}
{"Name": "['Guillermo']", "Lastname": "['Sanz']", "Lastname2": "['Gonzalez']", "Birthday": "['06/02/2014']"}
{"Name": "['Abel']", "Lastname": "['Vargas']", "Lastname2": "['Gallego']", "Birthday": "['17/10/2012']"}
{"Name": "['Sandra']", "Lastname": "['Gallego']", "Lastname2": "['Nunhez']", "Birthday": "['17/08/1993']"}
{"Name": "['Alexia']", "Lastname": "['Gimenez']", "Lastname2": "['Diez']", "Birthday": "['10/08/1984']"}
{"Name": "['Simon']", "Lastname": "['Mendez']", "Lastname2": "['Munhoz']", "Birthday": "['29/09/2019']"}
{"Name": "['Angela']", "Lastname": "['Roman']", "Lastname2": "['Ortega']", "Birthday": "['23/08/2002']"}
{"Name": "['Benjamin']", "Lastname": "['Ortega']", "Lastname2": "['Mendez']", "Birthday": "['08/01/2019']"}
{"Name": "['Lia']", "Lastname": "['Rubio']", "Lastname2": "['Nunhez']", "Birthday": "['28/11/2011']"}
{"Name": "['Adan']", "Lastname": "['Carrasco']", "Lastname2": "['Lozano']", "Birthday": "['04/08/1987']"}
{"Name": "['Javier']", "Lastname": "['Ortega']", "Lastname2": "['Calvo']", "Birthday": "['08/08/2016']"}
{"Name": "['Clara']", "Lastname": "['Hidalgo']", "Lastname2": "['Ortiz']", "Birthday": "['12/05/1998']"}
{"Name": "['Alex']", "Lastname": "['Montero']", "Lastname2": "['Soto']", "Birthday": "['21/09/2016']"}
{"Name": "['Camila']", "Lastname": "['Santiago']", "Lastname2": "['Ferrer']", "Birthday": "['01/11/1985']"}
{"Name": "['Viviana']", "Lastname": "['Fuentes']", "Lastname2": "['Cabrera']", "Birthday": "['20/07/2004']"}
{"Name": "['Victoria']", "Lastname": "['Campos']", "Lastname2": "['Gimenez']", "Birthday": "['01/10/1987']"}
{"Name": "['Santiago']", "Lastname": "['Cabrera']", "Lastname2": "['Ramos']", "Birthday": "['10/04/1987']"}
{"Name": "['Simon']", "Lastname": "['Ortega']", "Lastname2": "['Fuentes']", "Birthday": "['13/11/2009']"}
{"Name": "['Rafael']", "Lastname": "['Benitez']", "Lastname2": "['Torres']", "Birthday": "['26/09/1985']"}
{"Name": "['Matias']", "Lastname": "['Rodriguez']", "Lastname2": "['Molina']", "Birthday": "['05/02/1997']"}
{"Name": "['Adan']", "Lastname": "['Medina']", "Lastname2": "['Gil']", "Birthday": "['31/07/1991']"}
{"Name": "['Elias']", "Lastname": "['Sanchez']", "Lastname2": "['Bravo']", "Birthday": "['19/04/2018']"}
{"Name": "['Max']", "Lastname": "['Gallardo']", "Lastname2": "['Parra']", "Birthday": "['31/05/2018']"}
{"Name": "['Gloria']", "Lastname": "['Flores']", "Lastname2": "['Gomez']", "Birthday": "['16/04/2000']"}
{"Name": "['Estrella']", "Lastname": "['Reyes']", "Lastname2": "['Herrero']", "Birthday": "['25/08/1999']"}
{"Name": "['Lola']", "Lastname": "['Romero']", "Lastname2": "['Flores']", "Birthday": "['16/08/1997']"}
{"Name": "['Melina']", "Lastname": "['Benitez']", "Lastname2": "['Rubio']", "Birthday": "['03/10/2000']"}
{"Name": "['Jorge']", "Lastname": "['Santiago']", "Lastname2": "['Gallardo']", "Birthday": "['17/09/2018']"}
{"Name": "['Mauricio']", "Lastname": "['Ruiz']", "Lastname2": "['Herrero']", "Birthday": "['26/12/1998']"}
{"Name": "['Marina']", "Lastname": "['Moya']", "Lastname2": "['Perez']", "Birthday": "['25/03/1991']"}
{"Name": "['Eliana']", "Lastname": "['Herrero']", "Lastname2": "['Garrido']", "Birthday": "['14/03/1994']"}
{"Name": "['Alexis']", "Lastname": "['Navarro']", "Lastname2": "['Martinez']", "Birthday": "['03/09/2014']"}
{"Name": "['Olivia']", "Lastname": "['Reyes']", "Lastname2": "['Carmona']", "Birthday": "['08/08/1982']"}
{"Name": "['Esmeralda']", "Lastname": "['Duran']", "Lastname2": "['Marquez']", "Birthday": "['10/09/2004']"}
{"Name": "['Jose']", "Lastname": "['Arias']", "Lastname2": "['Calvo']", "Birthday": "['01/07/2013']"}
{"Name": "['Israel']", "Lastname": "['Delgado']", "Lastname2": "['Ibanhez']", "Birthday": "['19/02/2006']"}
{"Name": "['Monica']", "Lastname": "['Prieto']", "Lastname2": "['Marquez']", "Birthday": "['09/01/1992']"}
{"Name": "['Virginia']", "Lastname": "['Hidalgo']", "Lastname2": "['Reyes']", "Birthday": "['27/06/2017']"}
{"Name": "['Liliana']", "Lastname": "['Pastor']", "Lastname2": "['Calvo']", "Birthday": "['05/05/2003']"}
{"Name": "['Linda']", "Lastname": "['Iglesias']", "Lastname2": "['Gallardo']", "Birthday": "['07/02/1987']"}
{"Name": "['Ricardo']", "Lastname": "['Caballero']", "Lastname2": "['Rubio']", "Birthday": "['26/11/1995']"}
{"Name": "['Abraham']", "Lastname": "['Ibanhez']", "Lastname2": "['Vicente']", "Birthday": "['09/03/1985']"}
{"Name": "['Paola']", "Lastname": "['Rojas']", "Lastname2": "['Santos']", "Birthday": "['05/10/1987']"}
{"Name": "['Paola']", "Lastname": "['Rojas']", "Lastname2": "['Marquez']", "Birthday": "['26/12/1998']"}
{"Name": "['Juan']", "Lastname": "['Vidal']", "Lastname2": "['Pascual']", "Birthday": "['06/09/1991']"}
{"Name": "['Lilian']", "Lastname": "['Hernandez']", "Lastname2": "['Dominguez']", "Birthday": "['25/03/2021']"}
{"Name": "['Claudia']", "Lastname": "['Prieto']", "Lastname2": "['Nunhez']", "Birthday": "['28/05/1996']"}
{"Name": "['Juliana']", "Lastname": "['Lopez']", "Lastname2": "['Rodriguez']", "Birthday": "['21/02/1998']"}
{"Name": "['Ezequiel']", "Lastname": "['Duran']", "Lastname2": "['Reyes']", "Birthday": "['11/08/1995']"}
{"Name": "['Daniela']", "Lastname": "['Castillo']", "Lastname2": "['Cortes']", "Birthday": "['26/12/1985']"}
{"Name": "['Mateo']", "Lastname": "['Rojas']", "Lastname2": "['Moreno']", "Birthday": "['09/10/2020']"}
{"Name": "['Fabian']", "Lastname": "['Gallego']", "Lastname2": "['Duran']", "Birthday": "['14/04/2010']"}
{"Name": "['Rosa']", "Lastname": "['Benitez']", "Lastname2": "['Gil']", "Birthday": "['19/11/2009']"}
{"Name": "['Luis']", "Lastname": "['Suarez']", "Lastname2": "['Martinez']", "Birthday": "['10/02/1990']"}
{"Name": "['Ernesto']", "Lastname": "['Lorenzo']", "Lastname2": "['Vidal']", "Birthday": "['08/12/2015']"}
{"Name": "['Lucas']", "Lastname": "['Lopez']", "Lastname2": "['Alvarez']", "Birthday": "['01/09/1995']"}
{"Name": "['Ruben']", "Lastname": "['Lopez']", "Lastname2": "['Cabrera']", "Birthday": "['03/09/1982']"}
{"Name": "['Hugo']", "Lastname": "['Nunhez']", "Lastname2": "['Mendez']", "Birthday": "['21/06/2013']"}
{"Name": "['Alexis']", "Lastname": "['Vazquez']", "Lastname2": "['Morales']", "Birthday": "['21/02/1986']"}
{"Name": "['Tomas']", "Lastname": "['Sanz']", "Lastname2": "['Hernandez']", "Birthday": "['15/08/2010']"}
{"Name": "['Miriam']", "Lastname": "['Gomez']", "Lastname2": "['Castro']", "Birthday": "['07/12/1989']"}
{"Name": "['Oscar']", "Lastname": "['Leon']", "Lastname2": "['Serrano']", "Birthday": "['24/10/1993']"}
{"Name": "['Eduardo']", "Lastname": "['Marin']", "Lastname2": "['Gimenez']", "Birthday": "['23/03/2004']"}
{"Name": "['Nicolas']", "Lastname": "['Campos']", "Lastname2": "['Gomez']", "Birthday": "['23/07/2011']"}
{"Name": "['Adan']", "Lastname": "['Jimenez']", "Lastname2": "['Iglesias']", "Birthday": "['14/06/1987']"}
{"Name": "['Marisol']", "Lastname": "['Alonso']", "Lastname2": "['Campos']", "Birthday": "['12/10/1989']"}
{"Name": "['Lucian']", "Lastname": "['Santiago']", "Lastname2": "['Rubio']", "Birthday": "['31/10/1993']"}
{"Name": "['Roberto']", "Lastname": "['Marin']", "Lastname2": "['Esteban']", "Birthday": "['07/09/2012']"}
{"Name": "['Jairo']", "Lastname": "['Castro']", "Lastname2": "['Medina']", "Birthday": "['12/09/1983']"}
{"Name": "['Amaya']", "Lastname": "['Herrero']", "Lastname2": "['Santiago']", "Birthday": "['31/12/2013']"}
{"Name": "['Serena']", "Lastname": "['Alvarez']", "Lastname2": "['Rubio']", "Birthday": "['07/11/2008']"}
{"Name": "['Eduardo']", "Lastname": "['Reyes']", "Lastname2": "['Rojas']", "Birthday": "['16/05/1994']"}
{"Name": "['Alejandra']", "Lastname": "['Vazquez']", "Lastname2": "['Ruiz']", "Birthday": "['22/07/1997']"}
{"Name": "['Vivian']", "Lastname": "['Fernandez']", "Lastname2": "['Gil']", "Birthday": "['27/03/1997']"}
{"Name": "['Guillermo']", "Lastname": "['Moya']", "Lastname2": "['Ortiz']", "Birthday": "['14/07/2002']"}
{"Name": "['Esteban']", "Lastname": "['Serrano']", "Lastname2": "['Velasco']", "Birthday": "['26/10/2005']"}
{"Name": "['Mauricio']", "Lastname": "['Lorenzo']", "Lastname2": "['Suarez']", "Birthday": "['01/03/1982']"}
{"Name": "['Elsa']", "Lastname": "['Martinez']", "Lastname2": "['Bravo']", "Birthday": "['09/02/1994']"}
{"Name": "['Valeria']", "Lastname": "['Diez']", "Lastname2": "['Sanchez']", "Birthday": "['16/12/1982']"}
{"Name": "['Sandra']", "Lastname": "['Campos']", "Lastname2": "['Penha']", "Birthday": "['06/08/1987']"}
{"Name": "['Alicia']", "Lastname": "['Fuentes']", "Lastname2": "['Lorenzo']", "Birthday": "['27/04/1998']"}
{"Name": "['Juliana']", "Lastname": "['Benitez']", "Lastname2": "['Sanz']", "Birthday": "['31/10/2015']"}
{"Name": "['Alejandro']", "Lastname": "['Moya']", "Lastname2": "['Navarro']", "Birthday": "['01/06/1982']"}
{"Name": "['Josue']", "Lastname": "['Cano']", "Lastname2": "['Mendez']", "Birthday": "['04/04/1996']"}
{"Name": "['Sebastian']", "Lastname": "['Mora']", "Lastname2": "['Rojas']", "Birthday": "['04/08/2018']"}
{"Name": "['Eliana']", "Lastname": "['Gallardo']", "Lastname2": "['Diez']", "Birthday": "['16/01/2001']"}
{"Name": "['Javier']", "Lastname": "['Gimenez']", "Lastname2": "['Hernandez']", "Birthday": "['23/04/1999']"}
{"Name": "['Daniela']", "Lastname": "['Soler']", "Lastname2": "['Leon']", "Birthday": "['12/11/2021']"}
{"Name": "['Juliana']", "Lastname": "['Gonzalez']", "Lastname2": "['Benitez']", "Birthday": "['19/01/1990']"}
{"Name": "['Vivian']", "Lastname": "['Garrido']", "Lastname2": "['Pastor']", "Birthday": "['07/07/1999']"}
{"Name": "['Talia']", "Lastname": "['Parra']", "Lastname2": "['Romero']", "Birthday": "['16/08/1991']"}
{"Name": "['Guadalupe']", "Lastname": "['Delgado']", "Lastname2": "['Carmona']", "Birthday": "['18/02/1997']"}
{"Name": "['Luis']", "Lastname": "['Ramos']", "Lastname2": "['Vega']", "Birthday": "['06/01/1983']"}
{"Name": "['Ada']", "Lastname": "['Rubio']", "Lastname2": "['Leon']", "Birthday": "['17/05/2011']"}
{"Name": "['Daniela']", "Lastname": "['Ramos']", "Lastname2": "['Delgado']", "Birthday": "['06/02/1985']"}
{"Name": "['Veronica']", "Lastname": "['Pastor']", "Lastname2": "['Calvo']", "Birthday": "['18/09/1993']"}
{"Name": "['Matias']", "Lastname": "['Ortega']", "Lastname2": "['Campos']", "Birthday": "['07/10/1986']"}
{"Name": "['Diana']", "Lastname": "['Lopez']", "Lastname2": "['Marquez']", "Birthday": "['20/11/1997']"}
{"Name": "['Emilia']", "Lastname": "['Castro']", "Lastname2": "['Sanchez']", "Birthday": "['27/04/1990']"}
{"Name": "['Maximiliano']", "Lastname": "['Pastor']", "Lastname2": "['Montero']", "Birthday": "['26/02/2002']"}
{"Name": "['Orlando']", "Lastname": "['Martin']", "Lastname2": "['Martin']", "Birthday": "['05/01/2010']"}
{"Name": "['Maya']", "Lastname": "['Lopez']", "Lastname2": "['Rojas']", "Birthday": "['30/10/1990']"}
{"Name": "['Monica']", "Lastname": "['Herrero']", "Lastname2": "['Velasco']", "Birthday": "['16/06/1991']"}
{"Name": "['Paul']", "Lastname": "['Dominguez']", "Lastname2": "['Pastor']", "Birthday": "['07/04/1992']"}
{"Name": "['Ezequiel']", "Lastname": "['Marin']", "Lastname2": "['Martinez']", "Birthday": "['06/04/2014']"}
{"Name": "['Ruben']", "Lastname": "['Campos']", "Lastname2": "['Molina']", "Birthday": "['27/09/2013']"}
{"Name": "['Abraham']", "Lastname": "['Vidal']", "Lastname2": "['Navarro']", "Birthday": "['05/01/2020']"}
{"Name": "['Angelica']", "Lastname": "['Esteban']", "Lastname2": "['Navarro']", "Birthday": "['12/04/2017']"}
{"Name": "['Rodrigo']", "Lastname": "['Reyes']", "Lastname2": "['Benitez']", "Birthday": "['10/06/1994']"}
{"Name": "['Mateo']", "Lastname": "['Duran']", "Lastname2": "['Sanz']", "Birthday": "['23/12/2007']"}
{"Name": "['Viviana']", "Lastname": "['Prieto']", "Lastname2": "['Montero']", "Birthday": "['06/07/2011']"}
{"Name": "['Veronica']", "Lastname": "['Alonso']", "Lastname2": "['Saez']", "Birthday": "['11/08/1982']"}
{"Name": "['Angelica']", "Lastname": "['Lopez']", "Lastname2": "['Ortiz']", "Birthday": "['03/05/1997']"}
{"Name": "['Rosa']", "Lastname": "['Morales']", "Lastname2": "['Bravo']", "Birthday": "['21/04/2017']"}
{"Name": "['Camila']", "Lastname": "['Santana']", "Lastname2": "['Gil']", "Birthday": "['15/11/2010']"}
{"Name": "['Eliana']", "Lastname": "['Santana']", "Lastname2": "['Vidal']", "Birthday": "['10/09/2016']"}
{"Name": "['Francisco']", "Lastname": "['Rojas']", "Lastname2": "['Campos']", "Birthday": "['30/09/2010']"}
{"Name": "['Sara']", "Lastname": "['Fernandez']", "Lastname2": "['Ortega']", "Birthday": "['14/04/1992']"}
{"Name": "['Vivian']", "Lastname": "['Pastor']", "Lastname2": "['Santos']", "Birthday": "['30/10/2016']"}
{"Name": "['Jorge']", "Lastname": "['Duran']", "Lastname2": "['Pascual']", "Birthday": "['19/03/1999']"}
{"Name": "['Javier']", "Lastname": "['Lopez']", "Lastname2": "['Caballero']", "Birthday": "['07/10/2017']"}
{"Name": "['Sara']", "Lastname": "['Guerrero']", "Lastname2": "['Morales']", "Birthday": "['21/02/2003']"}
{"Name": "['Julia']", "Lastname": "['Torres']", "Lastname2": "['Vidal']", "Birthday": "['21/11/1992']"}
{"Name": "['Sandra']", "Lastname": "['Caballero']", "Lastname2": "['Caballero']", "Birthday": "['28/05/1990']"}
{"Name": "['Elena']", "Lastname": "['Ferrer']", "Lastname2": "['Rodriguez']", "Birthday": "['18/02/2011']"}
{"Name": "['Ariana']", "Lastname": "['Morales']", "Lastname2": "['Vidal']", "Birthday": "['29/09/2018']"}
{"Name": "['Jairo']", "Lastname": "['Cruz']", "Lastname2": "['Gutierrez']", "Birthday": "['28/04/2009']"}
{"Name": "['Marcos']", "Lastname": "['Ruiz']", "Lastname2": "['Gil']", "Birthday": "['06/10/1996']"}
{"Name": "['Lilian']", "Lastname": "['Munhoz']", "Lastname2": "['Garrido']", "Birthday": "['08/04/1994']"}
{"Name": "['Serena']", "Lastname": "['Ramirez']", "Lastname2": "['Gomez']", "Birthday": "['20/08/1998']"}
{"Name": "['Marina']", "Lastname": "['Marquez']", "Lastname2": "['Castillo']", "Birthday": "['15/06/1987']"}
{"Name": "['Israel']", "Lastname": "['Gomez']", "Lastname2": "['Ramos']", "Birthday": "['25/12/2014']"}
{"Name": "['Cecilia']", "Lastname": "['Munhoz']", "Lastname2": "['Perez']", "Birthday": "['11/06/2021']"}
{"Name": "['Diana']", "Lastname": "['Ruiz']", "Lastname2": "['Martin']", "Birthday": "['24/12/2006']"}
{"Name": "['Daniela']", "Lastname": "['Guerrero']", "Lastname2": "['Jimenez']", "Birthday": "['19/11/2004']"}
{"Name": "['Iris']", "Lastname": "['Lozano']", "Lastname2": "['Alonso']", "Birthday": "['29/08/2018']"}
{"Name": "['Alejandro']", "Lastname": "['Prieto']", "Lastname2": "['Munhoz']", "Birthday": "['25/05/2020']"}
{"Name": "['Abraham']", "Lastname": "['Fernandez']", "Lastname2": "['Ortega']", "Birthday": "['25/08/1984']"}
{"Name": "['Alexa']", "Lastname": "['Vazquez']", "Lastname2": "['Pastor']", "Birthday": "['24/05/2010']"}
{"Name": "['Abel']", "Lastname": "['Molina']", "Lastname2": "['Gimenez']", "Birthday": "['20/04/2009']"}
{"Name": "['Miranda']", "Lastname": "['Castro']", "Lastname2": "['Nieto']", "Birthday": "['18/03/1987']"}
{"Name": "['Roman']", "Lastname": "['Mendez']", "Lastname2": "['Montero']", "Birthday": "['01/01/1988']"}
{"Name": "['Jairo']", "Lastname": "['Navarro']", "Lastname2": "['Gonzalez']", "Birthday": "['25/11/1999']"}
{"Name": "['Mateo']", "Lastname": "['Gutierrez']", "Lastname2": "['Lozano']", "Birthday": "['15/04/2004']"}
{"Name": "['Pedro']", "Lastname": "['Nieto']", "Lastname2": "['Pastor']", "Birthday": "['14/10/1983']"}
{"Name": "['Matias']", "Lastname": "['Alvarez']", "Lastname2": "['Santana']", "Birthday": "['21/09/1992']"}
{"Name": "['Lucian']", "Lastname": "['Iglesias']", "Lastname2": "['Gallego']", "Birthday": "['20/04/1986']"}
{"Name": "['Jaime']", "Lastname": "['Navarro']", "Lastname2": "['Sanchez']", "Birthday": "['12/07/2019']"}
{"Name": "['Adriana']", "Lastname": "['Lozano']", "Lastname2": "['Lozano']", "Birthday": "['30/08/2006']"}
{"Name": "['Fernando']", "Lastname": "['Santana']", "Lastname2": "['Herrera']", "Birthday": "['04/11/2001']"}
{"Name": "['Ernesto']", "Lastname": "['Ramos']", "Lastname2": "['Molina']", "Birthday": "['01/09/2007']"}
{"Name": "['Linda']", "Lastname": "['Gallego']", "Lastname2": "['Cano']", "Birthday": "['15/12/2003']"}
{"Name": "['Lilian']", "Lastname": "['Moreno']", "Lastname2": "['Vicente']", "Birthday": "['16/09/1995']"}
{"Name": "['Manuel']", "Lastname": "['Ferrer']", "Lastname2": "['Campos']", "Birthday": "['18/01/2003']"}
{"Name": "['Esmeralda']", "Lastname": "['Aguilar']", "Lastname2": "['Diez']", "Birthday": "['31/07/2009']"}
{"Name": "['Ezequiel']", "Lastname": "['Cruz']", "Lastname2": "['Arias']", "Birthday": "['06/09/1983']"}
{"Name": "['Gloria']", "Lastname": "['Martinez']", "Lastname2": "['Vicente']", "Birthday": "['22/10/1987']"}
{"Name": "['Marcos']", "Lastname": "['Lorenzo']", "Lastname2": "['Lorenzo']", "Birthday": "['19/02/1984']"}
{"Name": "['Max']", "Lastname": "['Campos']", "Lastname2": "['Saez']", "Birthday": "['05/11/1984']"}
{"Name": "['Xavier']", "Lastname": "['Gomez']", "Lastname2": "['Fuentes']", "Birthday": "['18/12/1992']"}
{"Name": "['Julian']", "Lastname": "['Ruiz']", "Lastname2": "['Gomez']", "Birthday": "['13/08/2013']"}
{"Name": "['Alonzo']", "Lastname": "['Aguilar']", "Lastname2": "['Mora']", "Birthday": "['06/01/1983']"}
{"Name": "['Abraham']", "Lastname": "['Herrero']", "Lastname2": "['Gallardo']", "Birthday": "['20/01/1999']"}
{"Name": "['Esmeralda']", "Lastname": "['Cortes']", "Lastname2": "['Carrasco']", "Birthday": "['20/01/1990']"}
{"Name": "['Rafael']", "Lastname": "['Torres']", "Lastname2": "['Gimenez']", "Birthday": "['07/03/1987']"}
{"Name": "['Hugo']", "Lastname": "['Diaz']", "Lastname2": "['Rojas']", "Birthday": "['30/12/2014']"}
{"Name": "['Alejandro']", "Lastname": "['Moya']", "Lastname2": "['Santos']", "Birthday": "['14/03/2017']"}
{"Name": "['Edgar']", "Lastname": "['Montero']", "Lastname2": "['Gomez']", "Birthday": "['18/07/2000']"}
{"Name": "['Olivia']", "Lastname": "['Garrido']", "Lastname2": "['Lozano']", "Birthday": "['14/02/2017']"}
{"Name": "['Leonardo']", "Lastname": "['Campos']", "Lastname2": "['Lopez']", "Birthday": "['13/11/2021']"}
{"Name": "['Lia']", "Lastname": "['Lopez']", "Lastname2": "['Alonso']", "Birthday": "['07/01/2017']"}
{"Name": "['Maria']", "Lastname": "['Diaz']", "Lastname2": "['Campos']", "Birthday": "['06/12/2007']"}
{"Name": "['Angel']", "Lastname": "['Marin']", "Lastname2": "['Romero']", "Birthday": "['15/01/2001']"}
{"Name": "['Ramon']", "Lastname": "['Ibanhez']", "Lastname2": "['Rodriguez']", "Birthday": "['03/06/2021']"}
{"Name": "['Alejandro']", "Lastname": "['Gallego']", "Lastname2": "['Iglesias']", "Birthday": "['15/07/1999']"}
{"Name": "['Hector']", "Lastname": "['Nunhez']", "Lastname2": "['Moreno']", "Birthday": "['27/10/2011']"}
{"Name": "['Fernanda']", "Lastname": "['Diez']", "Lastname2": "['Soto']", "Birthday": "['17/05/1996']"}
{"Name": "['Ximena']", "Lastname": "['Vazquez']", "Lastname2": "['Fernandez']", "Birthday": "['03/02/2010']"}
{"Name": "['Armando']", "Lastname": "['Saez']", "Lastname2": "['Benitez']", "Birthday": "['22/06/2014']"}
{"Name": "['Marina']", "Lastname": "['Diaz']", "Lastname2": "['Ortiz']", "Birthday": "['31/07/2000']"}
{"Name": "['Angel']", "Lastname": "['Arias']", "Lastname2": "['Arias']", "Birthday": "['01/01/1984']"}
{"Name": "['Hugo']", "Lastname": "['Mora']", "Lastname2": "['Ortiz']", "Birthday": "['16/07/1995']"}
{"Name": "['Ada']", "Lastname": "['Crespo']", "Lastname2": "['Santos']", "Birthday": "['12/10/1992']"}
{"Name": "['Gabriela']", "Lastname": "['Moya']", "Lastname2": "['Vega']", "Birthday": "['03/05/2019']"}
{"Name": "['Amanda']", "Lastname": "['Duran']", "Lastname2": "['Carrasco']", "Birthday": "['28/06/1989']"}
{"Name": "['Emilia']", "Lastname": "['Prieto']", "Lastname2": "['Hidalgo']", "Birthday": "['13/08/2017']"}
{"Name": "['Martin']", "Lastname": "['Diez']", "Lastname2": "['Duran']", "Birthday": "['12/11/2002']"}
{"Name": "['Jairo']", "Lastname": "['Penha']", "Lastname2": "['Ortega']", "Birthday": "['07/07/1991']"}
{"Name": "['Roberto']", "Lastname": "['Hidalgo']", "Lastname2": "['Nieto']", "Birthday": "['06/10/1989']"}
{"Name": "['Luis']", "Lastname": "['Guerrero']", "Lastname2": "['Iglesias']", "Birthday": "['23/06/1995']"}
{"Name": "['David']", "Lastname": "['Vidal']", "Lastname2": "['Flores']", "Birthday": "['12/01/1996']"}
{"Name": "['Amanda']", "Lastname": "['Iglesias']", "Lastname2": "['Diez']", "Birthday": "['16/10/1996']"}
{"Name": "['Daniella']", "Lastname": "['Gutierrez']", "Lastname2": "['Martinez']", "Birthday": "['13/01/1988']"}
{"Name": "['Paul']", "Lastname": "['Gutierrez']", "Lastname2": "['Rojas']", "Birthday": "['06/02/2012']"}
{"Name": "['Diana']", "Lastname": "['Gutierrez']", "Lastname2": "['Alvarez']", "Birthday": "['01/01/2009']"}
{"Name": "['Fabian']", "Lastname": "['Parra']", "Lastname2": "['Nunhez']", "Birthday": "['09/11/2019']"}
{"Name": "['Arturo']", "Lastname": "['Moreno']", "Lastname2": "['Iglesias']", "Birthday": "['19/01/2003']"}
{"Name": "['Julian']", "Lastname": "['Nunhez']", "Lastname2": "['Moreno']", "Birthday": "['26/07/2015']"}
{"Name": "['Daniela']", "Lastname": "['Ramos']", "Lastname2": "['Morales']", "Birthday": "['16/10/2008']"}
{"Name": "['Javier']", "Lastname": "['Gallardo']", "Lastname2": "['Diez']", "Birthday": "['05/09/2018']"}
{"Name": "['Eduardo']", "Lastname": "['Fernandez']", "Lastname2": "['Prieto']", "Birthday": "['15/04/1990']"}
{"Name": "['Alfredo']", "Lastname": "['Carrasco']", "Lastname2": "['Moya']", "Birthday": "['10/07/1997']"}
{"Name": "['Ramon']", "Lastname": "['Soto']", "Lastname2": "['Perez']", "Birthday": "['07/12/2007']"}
{"Name": "['Fabian']", "Lastname": "['Calvo']", "Lastname2": "['Rojas']", "Birthday": "['29/06/2017']"}
{"Name": "['Emanuel']", "Lastname": "['Parra']", "Lastname2": "['Iglesias']", "Birthday": "['28/12/2016']"}
{"Name": "['Eliana']", "Lastname": "['Santana']", "Lastname2": "['Leon']", "Birthday": "['26/11/2014']"}
{"Name": "['Daniel']", "Lastname": "['Penha']", "Lastname2": "['Suarez']", "Birthday": "['02/11/2012']"}
{"Name": "['Selena']", "Lastname": "['Medina']", "Lastname2": "['Jimenez']", "Birthday": "['14/02/1987']"}
{"Name": "['Daniel']", "Lastname": "['Rojas']", "Lastname2": "['Bravo']", "Birthday": "['13/06/2004']"}
{"Name": "['Hugo']", "Lastname": "['Iglesias']", "Lastname2": "['Iglesias']", "Birthday": "['22/09/1992']"}
{"Name": "['Jose']", "Lastname": "['Ruiz']", "Lastname2": "['Alvarez']", "Birthday": "['16/10/2007']"}
{"Name": "['Alexandria']", "Lastname": "['Roman']", "Lastname2": "['Serrano']", "Birthday": "['07/08/2015']"}
{"Name": "['Andrea']", "Lastname": "['Soler']", "Lastname2": "['Navarro']", "Birthday": "['27/06/2007']"}
{"Name": "['Benjamin']", "Lastname": "['Medina']", "Lastname2": "['Esteban']", "Birthday": "['24/05/2008']"}
{"Name": "['Veronica']", "Lastname": "['Ibanhez']", "Lastname2": "['Vazquez']", "Birthday": "['17/10/2018']"}
{"Name": "['Guadalupe']", "Lastname": "['Parra']", "Lastname2": "['Diaz']", "Birthday": "['30/04/2015']"}
{"Name": "['Alejandro']", "Lastname": "['Castillo']", "Lastname2": "['Ramos']", "Birthday": "['13/09/2010']"}
{"Name": "['Leonardo']", "Lastname": "['Vicente']", "Lastname2": "['Iglesias']", "Birthday": "['11/10/2009']"}
{"Name": "['Alicia']", "Lastname": "['Soler']", "Lastname2": "['Castro']", "Birthday": "['11/08/1989']"}
{"Name": "['Perla']", "Lastname": "['Lorenzo']", "Lastname2": "['Lopez']", "Birthday": "['09/08/1991']"}
{"Name": "['David']", "Lastname": "['Calvo']", "Lastname2": "['Santos']", "Birthday": "['24/03/1999']"}
{"Name": "['Alana']", "Lastname": "['Gomez']", "Lastname2": "['Carmona']", "Birthday": "['13/04/2020']"}
{"Name": "['Maria']", "Lastname": "['Gil']", "Lastname2": "['Rojas']", "Birthday": "['04/02/1990']"}
{"Name": "['Arturo']", "Lastname": "['Penha']", "Lastname2": "['Hernandez']", "Birthday": "['21/12/2001']"}
{"Name": "['Angelica']", "Lastname": "['Alvarez']", "Lastname2": "['Calvo']", "Birthday": "['18/05/2009']"}
{"Name": "['Celeste']", "Lastname": "['Fuentes']", "Lastname2": "['Medina']", "Birthday": "['18/10/2003']"}
{"Name": "['Lucia']", "Lastname": "['Esteban']", "Lastname2": "['Rojas']", "Birthday": "['24/09/1988']"}
{"Name": "['Tomas']", "Lastname": "['Campos']", "Lastname2": "['Santana']", "Birthday": "['17/04/2021']"}
{"Name": "['Orlando']", "Lastname": "['Pastor']", "Lastname2": "['Roman']", "Birthday": "['25/11/2007']"}
{"Name": "['Cecilia']", "Lastname": "['Vazquez']", "Lastname2": "['Lozano']", "Birthday": "['14/03/2013']"}
{"Name": "['Mauricio']", "Lastname": "['Flores']", "Lastname2": "['Duran']", "Birthday": "['05/07/2001']"}
{"Name": "['Elsa']", "Lastname": "['Benitez']", "Lastname2": "['Gomez']", "Birthday": "['23/09/2017']"}
{"Name": "['Lola']", "Lastname": "['Gallego']", "Lastname2": "['Vidal']", "Birthday": "['15/09/1984']"}
{"Name": "['Jairo']", "Lastname": "['Pastor']", "Lastname2": "['Gallego']", "Birthday": "['03/09/2019']"}
{"Name": "['Isabel']", "Lastname": "['Penha']", "Lastname2": "['Herrera']", "Birthday": "['05/10/1984']"}
{"Name": "['Ada']", "Lastname": "['Martinez']", "Lastname2": "['Ruiz']", "Birthday": "['02/04/1982']"}
{"Name": "['Samuel']", "Lastname": "['Molina']", "Lastname2": "['Rojas']", "Birthday": "['02/11/2020']"}
{"Name": "['Adrian']", "Lastname": "['Caballero']", "Lastname2": "['Guerrero']", "Birthday": "['09/11/2003']"}
{"Name": "['Gustavo']", "Lastname": "['Esteban']", "Lastname2": "['Guerrero']", "Birthday": "['16/03/2012']"}
{"Name": "['Esmeralda']", "Lastname": "['Rojas']", "Lastname2": "['Serrano']", "Birthday": "['08/09/2010']"}
{"Name": "['Alonzo']", "Lastname": "['Mora']", "Lastname2": "['Martin']", "Birthday": "['24/11/2002']"}
{"Name": "['Valentina']", "Lastname": "['Munhoz']", "Lastname2": "['Munhoz']", "Birthday": "['12/10/1988']"}
{"Name": "['Asia']", "Lastname": "['Suarez']", "Lastname2": "['Soler']", "Birthday": "['25/02/1986']"}
{"Name": "['Jesus']", "Lastname": "['Santana']", "Lastname2": "['Flores']", "Birthday": "['06/06/1988']"}
{"Name": "['America']", "Lastname": "['Fernandez']", "Lastname2": "['Nieto']", "Birthday": "['27/04/1986']"}
{"Name": "['Emanuel']", "Lastname": "['Molina']", "Lastname2": "['Jimenez']", "Birthday": "['03/12/1986']"}
{"Name": "['Leonardo']", "Lastname": "['Moreno']", "Lastname2": "['Ramos']", "Birthday": "['06/01/2021']"}
{"Name": "['Camila']", "Lastname": "['Lorenzo']", "Lastname2": "['Penha']", "Birthday": "['28/06/2002']"}
{"Name": "['Alexia']", "Lastname": "['Campos']", "Lastname2": "['Gutierrez']", "Birthday": "['13/03/2012']"}
{"Name": "['Tobias']", "Lastname": "['Carrasco']", "Lastname2": "['Roman']", "Birthday": "['25/09/2017']"}
{"Name": "['Talia']", "Lastname": "['Pastor']", "Lastname2": "['Esteban']", "Birthday": "['06/04/2018']"}
{"Name": "['Paul']", "Lastname": "['Vargas']", "Lastname2": "['Marin']", "Birthday": "['12/05/2009']"}
{"Name": "['Veronica']", "Lastname": "['Molina']", "Lastname2": "['Romero']", "Birthday": "['14/05/1988']"}
{"Name": "['Adan']", "Lastname": "['Castro']", "Lastname2": "['Ortega']", "Birthday": "['19/03/2008']"}
{"Name": "['Angel']", "Lastname": "['Gomez']", "Lastname2": "['Martin']", "Birthday": "['04/03/1993']"}
{"Name": "['Jorge']", "Lastname": "['Nunhez']", "Lastname2": "['Vidal']", "Birthday": "['17/08/1995']"}
{"Name": "['Abram']", "Lastname": "['Moreno']", "Lastname2": "['Benitez']", "Birthday": "['11/05/2017']"}
{"Name": "['Elisa']", "Lastname": "['Cortes']", "Lastname2": "['Marin']", "Birthday": "['31/08/1999']"}
{"Name": "['David']", "Lastname": "['Velasco']", "Lastname2": "['Castro']", "Birthday": "['13/03/2021']"}
{"Name": "['Marisol']", "Lastname": "['Santana']", "Lastname2": "['Ibanhez']", "Birthday": "['20/03/1990']"}
{"Name": "['Virginia']", "Lastname": "['Carmona']", "Lastname2": "['Guerrero']", "Birthday": "['19/03/2013']"}
{"Name": "['Nicolas']", "Lastname": "['Guerrero']", "Lastname2": "['Mora']", "Birthday": "['13/09/1997']"}
{"Name": "['Liliana']", "Lastname": "['Alvarez']", "Lastname2": "['Torres']", "Birthday": "['18/02/2020']"}
{"Name": "['Alina']", "Lastname": "['Hernandez']", "Lastname2": "['Diaz']", "Birthday": "['14/08/1990']"}
{"Name": "['Serena']", "Lastname": "['Cabrera']", "Lastname2": "['Gonzalez']", "Birthday": "['27/11/2010']"}
{"Name": "['Laura']", "Lastname": "['Marquez']", "Lastname2": "['Molina']", "Birthday": "['26/06/1986']"}
{"Name": "['Hugo']", "Lastname": "['Blanco']", "Lastname2": "['Mora']", "Birthday": "['21/12/1999']"}
{"Name": "['Talia']", "Lastname": "['Saez']", "Lastname2": "['Moreno']", "Birthday": "['08/04/2020']"}
{"Name": "['Adrian']", "Lastname": "['Rojas']", "Lastname2": "['Soto']", "Birthday": "['05/01/1989']"}
{"Name": "['Paul']", "Lastname": "['Navarro']", "Lastname2": "['Diez']", "Birthday": "['22/09/2015']"}
{"Name": "['Juliana']", "Lastname": "['Perez']", "Lastname2": "['Parra']", "Birthday": "['01/02/1997']"}
{"Name": "['Sergio']", "Lastname": "['Duran']", "Lastname2": "['Hidalgo']", "Birthday": "['30/08/2004']"}
{"Name": "['Alfredo']", "Lastname": "['Gallardo']", "Lastname2": "['Reyes']", "Birthday": "['15/06/1999']"}
{"Name": "['Alan']", "Lastname": "['Benitez']", "Lastname2": "['Santiago']", "Birthday": "['14/09/1999']"}
{"Name": "['Abram']", "Lastname": "['Pastor']", "Lastname2": "['Moreno']", "Birthday": "['20/01/2011']"}
{"Name": "['Lucas']", "Lastname": "['Soler']", "Lastname2": "['Romero']", "Birthday": "['30/12/2010']"}
{"Name": "['Alexia']", "Lastname": "['Molina']", "Lastname2": "['Lozano']", "Birthday": "['30/09/1989']"}
{"Name": "['Xavier']", "Lastname": "['Alvarez']", "Lastname2": "['Munhoz']", "Birthday": "['17/12/2004']"}
{"Name": "['Diego']", "Lastname": "['Ferrer']", "Lastname2": "['Hernandez']", "Birthday": "['16/01/1986']"}
{"Name": "['Ricardo']", "Lastname": "['Lozano']", "Lastname2": "['Ramos']", "Birthday": "['23/11/1999']"}
{"Name": "['Cesar']", "Lastname": "['Crespo']", "Lastname2": "['Suarez']", "Birthday": "['19/08/2003']"}
{"Name": "['Alex']", "Lastname": "['Diez']", "Lastname2": "['Medina']", "Birthday": "['27/03/2000']"}
{"Name": "['Adrian']", "Lastname": "['Carmona']", "Lastname2": "['Leon']", "Birthday": "['18/02/1994']"}
{"Name": "['Martin']", "Lastname": "['Vargas']", "Lastname2": "['Molina']", "Birthday": "['14/09/1993']"}
{"Name": "['Ernesto']", "Lastname": "['Lozano']", "Lastname2": "['Carrasco']", "Birthday": "['30/07/2001']"}
{"Name": "['Natalia']", "Lastname": "['Santos']", "Lastname2": "['Gonzalez']", "Birthday": "['07/02/1985']"}
{"Name": "['Victoria']", "Lastname": "['Aguilar']", "Lastname2": "['Rodriguez']", "Birthday": "['10/05/2012']"}
{"Name": "['Roman']", "Lastname": "['Blanco']", "Lastname2": "['Marquez']", "Birthday": "['09/10/2012']"}
{"Name": "['Alex']", "Lastname": "['Fuentes']", "Lastname2": "['Pastor']", "Birthday": "['31/10/1985']"}
{"Name": "['Emilia']", "Lastname": "['Moreno']", "Lastname2": "['Herrero']", "Birthday": "['10/09/2012']"}
{"Name": "['Valeria']", "Lastname": "['Navarro']", "Lastname2": "['Calvo']", "Birthday": "['01/09/2005']"}
{"Name": "['Alana']", "Lastname": "['Vicente']", "Lastname2": "['Carmona']", "Birthday": "['27/04/2003']"}
{"Name": "['Hector']", "Lastname": "['Rodriguez']", "Lastname2": "['Saez']", "Birthday": "['16/09/1993']"}
{"Name": "['Julian']", "Lastname": "['Lorenzo']", "Lastname2": "['Benitez']", "Birthday": "['05/10/2015']"}
{"Name": "['Alejandra']", "Lastname": "['Morales']", "Lastname2": "['Dominguez']", "Birthday": "['10/05/1988']"}
{"Name": "['Fabian']", "Lastname": "['Rojas']", "Lastname2": "['Gutierrez']", "Birthday": "['21/02/1984']"}
{"Name": "['Ricardo']", "Lastname": "['Gonzalez']", "Lastname2": "['Navarro']", "Birthday": "['26/08/1982']"}
{"Name": "['Virginia']", "Lastname": "['Fernandez']", "Lastname2": "['Flores']", "Birthday": "['09/09/1984']"}
{"Name": "['Guillermo']", "Lastname": "['Dominguez']", "Lastname2": "['Gil']", "Birthday": "['10/08/2015']"}
{"Name": "['Carlos']", "Lastname": "['Suarez']", "Lastname2": "['Soler']", "Birthday": "['10/02/2009']"}
{"Name": "['Alonzo']", "Lastname": "['Diaz']", "Lastname2": "['Ortega']", "Birthday": "['09/02/1983']"}
{"Name": "['Paul']", "Lastname": "['Soler']", "Lastname2": "['Gonzalez']", "Birthday": "['14/08/2007']"}
{"Name": "['Roman']", "Lastname": "['Cabrera']", "Lastname2": "['Cano']", "Birthday": "['08/02/2006']"}
{"Name": "['Monica']", "Lastname": "['Pastor']", "Lastname2": "['Pastor']", "Birthday": "['20/10/1983']"}
{"Name": "['Guillermo']", "Lastname": "['Molina']", "Lastname2": "['Moreno']", "Birthday": "['04/11/2015']"}
{"Name": "['Alan']", "Lastname": "['Molina']", "Lastname2": "['Hernandez']", "Birthday": "['31/01/2015']"}
{"Name": "['Hugo']", "Lastname": "['Carmona']", "Lastname2": "['Ortega']", "Birthday": "['25/03/1983']"}
{"Name": "['Miranda']", "Lastname": "['Cortes']", "Lastname2": "['Gutierrez']", "Birthday": "['28/01/2020']"}
{"Name": "['Angela']", "Lastname": "['Campos']", "Lastname2": "['Rojas']", "Birthday": "['31/05/2012']"}
{"Name": "['Maya']", "Lastname": "['Gallardo']", "Lastname2": "['Leon']", "Birthday": "['28/01/2017']"}
{"Name": "['Hector']", "Lastname": "['Moreno']", "Lastname2": "['Molina']", "Birthday": "['25/02/1990']"}
{"Name": "['Manuel']", "Lastname": "['Roman']", "Lastname2": "['Rojas']", "Birthday": "['05/01/2007']"}
{"Name": "['Alana']", "Lastname": "['Castro']", "Lastname2": "['Flores']", "Birthday": "['11/09/2008']"}
{"Name": "['Adrian']", "Lastname": "['Montero']", "Lastname2": "['Gil']", "Birthday": "['06/04/1987']"}
{"Name": "['Mauricio']", "Lastname": "['Nunhez']", "Lastname2": "['Alvarez']", "Birthday": "['01/09/2001']"}
{"Name": "['Oscar']", "Lastname": "['Crespo']", "Lastname2": "['Leon']", "Birthday": "['12/09/2012']"}
{"Name": "['Ana']", "Lastname": "['Martinez']", "Lastname2": "['Medina']", "Birthday": "['18/04/2018']"}
{"Name": "['America']", "Lastname": "['Fernandez']", "Lastname2": "['Alonso']", "Birthday": "['28/02/1996']"}
{"Name": "['Orlando']", "Lastname": "['Gonzalez']", "Lastname2": "['Fuentes']", "Birthday": "['07/02/1982']"}
{"Name": "['Lucian']", "Lastname": "['Torres']", "Lastname2": "['Roman']", "Birthday": "['17/03/2020']"}
{"Name": "['Marco']", "Lastname": "['Ortega']", "Lastname2": "['Gallardo']", "Birthday": "['12/11/2013']"}
{"Name": "['Fatima']", "Lastname": "['Nieto']", "Lastname2": "['Campos']", "Birthday": "['31/07/2002']"}
{"Name": "['Pablo']", "Lastname": "['Aguilar']", "Lastname2": "['Flores']", "Birthday": "['03/02/1990']"}
{"Name": "['Mauricio']", "Lastname": "['Marquez']", "Lastname2": "['Caballero']", "Birthday": "['05/07/2002']"}
{"Name": "['Alfredo']", "Lastname": "['Castillo']", "Lastname2": "['Vargas']", "Birthday": "['30/09/2021']"}
{"Name": "['Valentina']", "Lastname": "['Delgado']", "Lastname2": "['Diaz']", "Birthday": "['12/12/1990']"}
{"Name": "['Jorge']", "Lastname": "['Alonso']", "Lastname2": "['Delgado']", "Birthday": "['26/06/2011']"}
{"Name": "['Roman']", "Lastname": "['Ruiz']", "Lastname2": "['Marquez']", "Birthday": "['21/05/2020']"}
{"Name": "['Daniela']", "Lastname": "['Martin']", "Lastname2": "['Pastor']", "Birthday": "['17/06/2011']"}
{"Name": "['Ivan']", "Lastname": "['Vazquez']", "Lastname2": "['Hernandez']", "Birthday": "['31/12/2016']"}
{"Name": "['Cecilia']", "Lastname": "['Guerrero']", "Lastname2": "['Nieto']", "Birthday": "['11/02/2020']"}
{"Name": "['Maximiliano']", "Lastname": "['Cruz']", "Lastname2": "['Castro']", "Birthday": "['13/10/1998']"}
{"Name": "['Sebastian']", "Lastname": "['Herrera']", "Lastname2": "['Cortes']", "Birthday": "['11/08/1985']"}
{"Name": "['Mariana']", "Lastname": "['Carmona']", "Lastname2": "['Nieto']", "Birthday": "['27/08/2004']"}
{"Name": "['Carmen']", "Lastname": "['Ortega']", "Lastname2": "['Diaz']", "Birthday": "['12/07/2000']"}
{"Name": "['Paola']", "Lastname": "['Carmona']", "Lastname2": "['Prieto']", "Birthday": "['30/12/2003']"}
{"Name": "['Alina']", "Lastname": "['Carmona']", "Lastname2": "['Dominguez']", "Birthday": "['09/10/1997']"}
